polyner/__init__.py
polyner/core.py
polyner/emoji_handling.py
polyner/entity_recognition.py
polyner/language_detection.py
polyner/tokenization.py
polyner/utils.py
polyner-0.1.0.dist-info/licenses/LICENSE
polyner-0.1.0.dist-info/METADATA
polyner-0.1.0.dist-info/WHEEL
polyner-0.1.0.dist-info/top_level.txt
polyner-0.1.0.dist-info/RECORD
