Metadata-Version: 2.4
Name: polyner
Version: 0.1.0
Summary: A multilingual NER library that handles text, emojis, and multiple languages
Author-email: PolyNER Team <example@example.com>
License: MIT
Project-URL: Bug Tracker, https://github.com/example/polyner/issues
Project-URL: Source Code, https://github.com/example/polyner
Classifier: Programming Language :: Python :: 3
Classifier: Programming Language :: Python :: 3.7
Classifier: Programming Language :: Python :: 3.8
Classifier: Programming Language :: Python :: 3.9
Classifier: Programming Language :: Python :: 3.10
Classifier: Programming Language :: Python :: 3.11
Classifier: Programming Language :: Python :: 3.12
Classifier: License :: OSI Approved :: MIT License
Classifier: Operating System :: OS Independent
Classifier: Intended Audience :: Developers
Classifier: Intended Audience :: Science/Research
Classifier: Topic :: Scientific/Engineering :: Artificial Intelligence
Classifier: Topic :: Text Processing :: Linguistic
Requires-Python: >=3.7
License-File: LICENSE
Requires-Dist: pandas>=1.0.0
Requires-Dist: langdetect>=1.0.7
Requires-Dist: emoji>=1.2.0
Requires-Dist: spacy>=3.0.0
Provides-Extra: dev
Requires-Dist: pytest>=7.0.0; extra == "dev"
Requires-Dist: pytest-cov>=3.0.0; extra == "dev"
Requires-Dist: flake8>=4.0.0; extra == "dev"
Requires-Dist: mypy>=0.9.0; extra == "dev"
Requires-Dist: black>=22.0.0; extra == "dev"
Requires-Dist: isort>=5.0.0; extra == "dev"
Requires-Dist: build>=0.8.0; extra == "dev"
Requires-Dist: twine>=4.0.0; extra == "dev"
Dynamic: license-file
